README.md
setup.py
./__init__.py
./cx_setup.py
./foundry_data_browser.py
./viewers/APD_ASI_2DSlowScanView.py
./viewers/APD_MCL_2DSlowScanView.py
./viewers/WinSpecMCL2DSlowScanView.py
./viewers/__init__.py
./viewers/andor_ccd_readout.py
./viewers/apd_confocal_npz.py
./viewers/auger_spec_map.py
./viewers/auger_spectrum_h5.py
./viewers/auger_sync_raster_scan.py
./viewers/auger_sync_raster_scan_h5.py
./viewers/drift_correction.py
./viewers/gauss2d_fit_img.py
./viewers/h5_tree.py
./viewers/hyperspec_3d_h5.py
./viewers/hyperspec_cl_h5.py
./viewers/hyperspec_h5.py
./viewers/hyperspec_npz.py
./viewers/images.py
./viewers/iv_h5.py
./viewers/picoharp_histogram_h5.py
./viewers/picoharp_mcl_2dslowscan.py
./viewers/picoharp_npz.py
./viewers/picoquant_histogram_h5.py
./viewers/power_scan_h5.py
./viewers/power_scan_npz.py
./viewers/power_spec_logger_view.py
./viewers/scalebars.py
./viewers/spectrum_h5.py
./viewers/sync_raster_scan_h5.py
./viewers/trpl_h5.py
./viewers/trpl_npz.py
./viewers/trpl_t_x_lifetime.py
./viewers/winspec_remote_readout_h5.py
FoundryDataBrowser.egg-info/PKG-INFO
FoundryDataBrowser.egg-info/SOURCES.txt
FoundryDataBrowser.egg-info/dependency_links.txt
FoundryDataBrowser.egg-info/entry_points.txt
FoundryDataBrowser.egg-info/requires.txt
FoundryDataBrowser.egg-info/top_level.txt