Metadata-Version: 1.0
Name: FoundryDataBrowser
Version: 190903.1
Summary: Data Browser for Foundry microscope data files
Home-page: http://www.scopefoundry.org/
Author: Edward S. Barnard
Author-email: esbarnard@lbl.gov
License: BSD
Platform: UNKNOWN
